{
  "commits" : [
    {
      "name" : "spirv-tools",
      "site" : "github",
      "subrepo" : "KhronosGroup/SPIRV-Tools",
      "subdir" : "External/spirv-tools",
      "commit": "5f4b62de998d161ee01e6f7706da2d855f8fcdc8"
    },
    {
      "name" : "spirv-tools/external/spirv-headers",
      "site" : "github",
      "subrepo" : "KhronosGroup/SPIRV-Headers",
      "subdir" : "External/spirv-tools/external/spirv-headers",
      "commit" : "04f10f650d514df88b76d25e83db360142c7b174"
    },
    {
      "name": "googletest",
      "site": "github",
      "subrepo": "google/googletest",
      "subdir": "External/googletest",
      "commit": "v1.14.0"
    }
  ]
}
